oddsprout/__init__.py
oddsprout/__main__.py
oddsprout/configuration.py
oddsprout/constants.py
oddsprout/exceptions.py
oddsprout/generators.py
oddsprout/py.typed
oddsprout/utils.py
oddsprout-0.1.1.dist-info/LICENSE
oddsprout-0.1.1.dist-info/METADATA
oddsprout-0.1.1.dist-info/WHEEL
oddsprout-0.1.1.dist-info/entry_points.txt
oddsprout-0.1.1.dist-info/RECORD
