Metadata-Version: 2.1
Name: oddsprout
Version: 0.1.1
Summary: Generate random JSON with no schemas involved
License: MIT
Author: trag1c
Author-email: trag1cdev@yahoo.com
Requires-Python: >=3.9,<4.0
Classifier: License :: OSI Approved :: MIT License
Classifier: Programming Language :: Python :: 3
Classifier: Programming Language :: Python :: 3.9
Classifier: Programming Language :: Python :: 3.10
Classifier: Programming Language :: Python :: 3.11
Classifier: Programming Language :: Python :: 3.12
Requires-Dist: dahlia (>=3.0.0,<4.0.0)
Requires-Dist: ixia (>=1.3.2,<2.0.0)
Requires-Dist: tomli (>=2.0.1,<3.0.0) ; python_version < "3.11"
